bot_config/__init__.py
bot_config/config.py
bot_config/models/__init__.py
bot_config/models/acc.py
bot_config/models/amazon_settings.py
bot_config/models/constants.py
bot_config/models/facebook_acc.py
bot_config/models/login_details.py
bot_config/models/proxy_details.py
bot_config-0.2.19.dist-info/METADATA
bot_config-0.2.19.dist-info/WHEEL
bot_config-0.2.19.dist-info/top_level.txt
bot_config-0.2.19.dist-info/RECORD
