Metadata-Version: 2.1
Name: bot-config
Version: 0.2.19
Summary: bot_config
Home-page: https://github.com/kopnt/bot_config
Author: Kristof & Zselter
License: UNKNOWN
Platform: UNKNOWN
Classifier: Programming Language :: Python :: 3
Classifier: License :: OSI Approved :: MIT License
Classifier: Operating System :: OS Independent
Requires-Python: >=3.5
Requires-Dist: amazon-config
Requires-Dist: selenium-uploader-account
Requires-Dist: kcu
Requires-Dist: amazon-platform
Requires-Dist: selenium-twitter
Requires-Dist: selenium-instagram
Requires-Dist: selenium-facebook
Requires-Dist: selenium-tiktok
Requires-Dist: simple-multiprocessing
Requires-Dist: selenium-youtube
